tj_tpauth/__init__.py
tj_tpauth/tj_tpauth.py
tj_tpauth-1.1.0.dist-info/LICENSE
tj_tpauth-1.1.0.dist-info/METADATA
tj_tpauth-1.1.0.dist-info/WHEEL
tj_tpauth-1.1.0.dist-info/RECORD
