Metadata-Version: 2.1
Name: tj-tpauth
Version: 1.1.0
Summary: Python library simplifies the process of authenticating accounts with TP Servers.
Author: Duy Nguyen
Author-email: duynguyen02.dev@gmail.com
Requires-Python: >=3.8,<4.0
Classifier: Programming Language :: Python :: 3
Classifier: Programming Language :: Python :: 3.8
Classifier: Programming Language :: Python :: 3.9
Classifier: Programming Language :: Python :: 3.10
Classifier: Programming Language :: Python :: 3.11
Classifier: Programming Language :: Python :: 3.12
Requires-Dist: aiohttp (>=3.10.5,<4.0.0)
Requires-Dist: requests (>=2.32.3,<3.0.0)
